intertidal_locator.py
intertidal_locator-1.0.0.dist-info/LICENSE
intertidal_locator-1.0.0.dist-info/METADATA
intertidal_locator-1.0.0.dist-info/WHEEL
intertidal_locator-1.0.0.dist-info/top_level.txt
intertidal_locator-1.0.0.dist-info/RECORD
