Metadata-Version: 2.1
Name: intertidal-locator
Version: 1.0.0
Summary: Tool to retrieve intertidal areas.
Author-email: ThomasPDM <thomas.pelissie_de_montemont@univ-lr.fr>
Maintainer-email: ThomasPDM <thomas.pelissie_de_montemont@univ-lr.fr>
License: MIT
Project-URL: repository, https://github.com/Hydraumath/intertidal-locator
Project-URL: Homepage, https://github.com/Hydraumath/intertidal-locator
Project-URL: Bug Tracker, https://github.com/Hydraumath/intertidal-locator/issues
Classifier: Programming Language :: Python :: 3
Classifier: License :: OSI Approved :: MIT License
Classifier: Operating System :: OS Independent
Requires-Python: >=3.9
License-File: LICENSE
Requires-Dist: numpy
Requires-Dist: Pillow
Requires-Dist: requests
